{
  "version": "7",
  "dialect": "postgresql",
  "entries": [
    {
      "idx": 0,
      "version": "7",
      "when": 1752323600309,
      "tag": "0000_amused_apocalypse",
      "breakpoints": true
    },
    {
      "idx": 1,
      "version": "7",
      "when": 1752324304879,
      "tag": "0001_brave_pet_avengers",
      "breakpoints": true
    },
    {
      "idx": 2,
      "version": "7",
      "when": 1752325886336,
      "tag": "0002_public_luminals",
      "breakpoints": true
    },
    {
      "idx": 3,
      "version": "7",
      "when": 1752326818577,
      "tag": "0003_heavy_maggott",
      "breakpoints": true
    },
    {
      "idx": 4,
      "version": "7",
      "when": 1752482166513,
      "tag": "0004_brown_bloodstrike",
      "breakpoints": true
    },
    {
      "idx": 5,
      "version": "7",
      "when": 1752661213066,
      "tag": "0005_medical_nico_minoru",
      "breakpoints": true
    }
  ]
}